ydoc_theme/__init__.py
ydoc_theme/breadcrumbs.html
ydoc_theme/footer.html
ydoc_theme/layout.html
ydoc_theme/search.html
ydoc_theme/searchbox.html
ydoc_theme/theme.conf
ydoc_theme/versions.html
ydoc_theme/static/css/badge_only.css
ydoc_theme/static/css/copied_wy_variables.css
ydoc_theme/static/css/theme.css
ydoc_theme/static/fonts/Inconsolata-Bold.ttf
ydoc_theme/static/fonts/Inconsolata-Regular.ttf
ydoc_theme/static/fonts/Lato-Bold.ttf
ydoc_theme/static/fonts/Lato-Regular.ttf
ydoc_theme/static/fonts/RobotoSlab-Bold.ttf
ydoc_theme/static/fonts/RobotoSlab-Regular.ttf
ydoc_theme/static/fonts/UbuntuMono-Bold.ttf
ydoc_theme/static/fonts/UbuntuMono-BoldItalic.ttf
ydoc_theme/static/fonts/UbuntuMono-Italic.ttf
ydoc_theme/static/fonts/UbuntuMono-Regular.ttf
ydoc_theme/static/fonts/fontawesome-webfont.eot
ydoc_theme/static/fonts/fontawesome-webfont.svg
ydoc_theme/static/fonts/fontawesome-webfont.ttf
ydoc_theme/static/fonts/fontawesome-webfont.woff
ydoc_theme/static/js/modernizr.min.js
ydoc_theme/static/js/theme.js
ydoc_theme-1.0.dist-info/LICENSE
ydoc_theme-1.0.dist-info/METADATA
ydoc_theme-1.0.dist-info/WHEEL
ydoc_theme-1.0.dist-info/entry_points.txt
ydoc_theme-1.0.dist-info/top_level.txt
ydoc_theme-1.0.dist-info/RECORD
